datasette_profiles/__init__.py
datasette_profiles/hookspecs.py
datasette_profiles/static/avatar-web-component.js
datasette_profiles/templates/edit_profile.html
datasette_profiles/templates/list_profiles.html
datasette_profiles/templates/profile.html
datasette_profiles-0.1a5.dist-info/licenses/LICENSE
datasette_profiles-0.1a5.dist-info/METADATA
datasette_profiles-0.1a5.dist-info/WHEEL
datasette_profiles-0.1a5.dist-info/entry_points.txt
datasette_profiles-0.1a5.dist-info/top_level.txt
datasette_profiles-0.1a5.dist-info/RECORD
