Metadata-Version: 2.4
Name: datasette-profiles
Version: 0.1a5
Summary: Editable user profile pages for Datasette
Author: Simon Willison
License-Expression: Apache-2.0
Project-URL: Homepage, https://github.com/datasette/datasette-profiles
Project-URL: Changelog, https://github.com/datasette/datasette-profiles/releases
Project-URL: Issues, https://github.com/datasette/datasette-profiles/issues
Project-URL: CI, https://github.com/datasette/datasette-profiles/actions
Classifier: Framework :: Datasette
Requires-Python: >=3.10
License-File: LICENSE
Requires-Dist: datasette>=1.0a21
Provides-Extra: test
Requires-Dist: pytest; extra == "test"
Requires-Dist: pytest-asyncio; extra == "test"
Dynamic: license-file
